ardmediathek_cli/__init__.py
ardmediathek_cli-1.0.2.dist-info/LICENSE
ardmediathek_cli-1.0.2.dist-info/METADATA
ardmediathek_cli-1.0.2.dist-info/WHEEL
ardmediathek_cli-1.0.2.dist-info/entry_points.txt
ardmediathek_cli-1.0.2.dist-info/top_level.txt
ardmediathek_cli-1.0.2.dist-info/RECORD
